[
    {
        "start": "00:00:21,040",
        "end": "00:00:23,920",
        "en": "Pada zaman dahulu…",
        "pa": "Once upon a time…",
        "vi": "Ngày xửa ngày xưa…"
    },
    {
        "start": "00:00:42,200",
        "end": "00:00:43,120",
        "en": "Comelnya Kiki!",
        "pa": "Kiki, you're so cute!",
        "vi": "Kiki dễ thương quá!"
    },
    {
        "start": "00:00:43,960",
        "end": "00:00:47,560",
        "en": "Kenapa tak masukkan baju dalam beg?",
        "pa": "Why don't you put those clothes in the bag?",
        "vi": "Sao cháu không cho mớ quần áo đó vào ba lô?"
    },
    {
        "start": "00:00:48,240",
        "end": "00:00:51,960",
        "en": "Tinggal sini sajalah. Cuti sekolah nanti Aris datang lagi.",
        "pa": "We'll just leave them here.\n I'll come back here during the school holidays.",
        "vi": "Chúng cháu để mấy cái đó lại.\n Cháu sẽ quay trở lại khi được nghỉ học."
    },
    {
        "start": "00:00:52,040",
        "end": "00:00:53,600",
        "en": "- Itu betul. - Hore!",
        "pa": "Yes, yes, yes.",
        "vi": "Phải thế chứ."
    },
    {
        "start": "00:00:55,280",
        "end": "00:00:57,600",
        "en": "Ara pun nak tinggalkan Kiki.",
        "pa": "I'll leave Kiki here too. She'll keep you company, Aki.",
        "vi": "Cháu cũng sẽ để Kiki ở lại. Nó sẽ bầu bạn với ông."
    },
    {
        "start": "00:00:57,680",
        "end": "00:01:00,040",
        "en": "Boleh temankan Aki.",
        "pa": "",
        "vi": ""
    },
    {
        "start": "00:01:07,400",
        "end": "00:01:10,000",
        "en": "Jaga Kiki baik-baik tahu!",
        "pa": "Take good care of Kiki!",
        "vi": "Ông chăm sóc Kiki cẩn thận nhé!"
    },
    {
        "start": "00:01:12,080",
        "end": "00:01:13,320",
        "en": "Baiklah.",
        "pa": "Alright.",
        "vi": "Được rồi."
    },
    {
        "start": "00:01:25,320",
        "end": "00:01:28,320",
        "en": "Tak apalah Ara. Bawa sajalah Kiki balik.",
        "pa": "It's alright, Ara. Just take Kiki home.",
        "vi": "Được rồi, Ara. Cháu mang Kiki về nhà đi."
    },
    {
        "start": "00:01:33,320",
        "end": "00:01:35,320",
        "en": "Bila dah kemas semua, mari ikut Aki.",
        "pa": "When you're done packing, follow me.",
        "vi": "Khi nào thu xếp đồ đạc xong thì theo ông."
    },
    {
        "start": "00:01:36,200",
        "end": "00:01:38,880",
        "en": "Tapi Aris nak tunggu Papa dengan Mama.",
        "pa": "But I want to wait for dad and mom.",
        "vi": "Nhưng cháu muốn đợi bố mẹ đến."
    },
    {
        "start": "00:01:41,920",
        "end": "00:01:44,080",
        "en": "Dia orang sampai malam nanti.",
        "pa": "They'll arrive later tonight.",
        "vi": "Bố mẹ các cháu đến tối mới đến."
    },
    {
        "start": "00:01:46,120",
        "end": "00:01:48,200",
        "en": "Sekarang ikut Aki pergi kenduri.",
        "pa": "Now, follow me to a ceremony.",
        "vi": "Giờ đi theo ông đến dự một buổi lễ nào."
    },
    {
        "start": "00:01:48,280",
        "end": "00:01:51,280",
        "en": "Bolehlah bergaul dan berkawan dengan budak-budak di situ.",
        "pa": "You can meet and make friends with other kids there.",
        "vi": "Các cháu có thể gặp gỡ và kết bạn với những đứa trẻ ở đó."
    },
    {
        "start": "00:01:51,920",
        "end": "00:01:55,240",
        "en": "Tak naklah. Baik duduk rumah. Boleh main permainan.",
        "pa": "I don't want to. Better stay home and play games.",
        "vi": "Cháu không muốn đi. Cháu thà ở nhà và chơi trò chơi điện tử."
    },
    {
        "start": "00:01:55,320",
        "end": "00:01:58,640",
        "en": "Ara pun. Main dengan Kiki lagi seronok.",
        "pa": "Me too. Playing with Kiki is way more fun.",
        "vi": "Cháu cũng vậy. Chơi với Kiki vui hơn."
    },
    {
        "start": "00:01:58,720",
        "end": "00:02:00,680",
        "en": "Dekat luar panas.",
        "pa": "-Outside is hot. -Ouch!",
        "vi": "Bên ngoài nóng lắm."
    },
    {
        "start": "00:02:00,760",
        "end": "00:02:01,800",
        "en": "Aduh.",
        "pa": "",
        "vi": ""
    },
    {
        "start": "00:02:02,320",
        "end": "00:02:05,640",
        "en": "Jangan ikut perangai Kera. Sombong!",
        "pa": "Don't follow Kera's arrogant attitude!",
        "vi": "Đừng bắt chước thái độ kiêu ngạo của Kera."
    },
    {
        "start": "00:02:08,560",
        "end": "00:02:11,520",
        "en": "Aki! Tak baik cakap macam itu.",
        "pa": "Aki, that's not nice.",
        "vi": "Ông à, nói vậy là không tốt."
    },
    {
        "start": "00:02:12,040",
        "end": "00:02:13,000",
        "en": "Memang betul.",
        "pa": "But it's true.",
        "vi": "Nhưng đúng là vậy mà."
    },
    {
        "start": "00:02:13,640",
        "end": "00:02:16,520",
        "en": "Sesiapa yang tak suka bergaul dan berkawan dengan orang,",
        "pa": "Whoever doesn't want to meet or be friends with anyone",
        "vi": "Bất cứ ai không muốn gặp gỡ hay kết bạn với bất kì ai"
    },
    {
        "start": "00:02:16,600",
        "end": "00:02:17,920",
        "en": "dipanggil \"Kera sumbang\".",
        "pa": "is called the odd man out.",
        "vi": "sẽ bị gọi là lập dị."
    },
    {
        "start": "00:02:18,000",
        "end": "00:02:21,360",
        "en": "Nanti orang pun tak suka dengan kita!",
        "pa": "One day, other people won't even like you!",
        "vi": "Rồi đến một ngày, người khác sẽ không thích cháu nữa!"
    },
    {
        "start": "00:02:24,040",
        "end": "00:02:27,720",
        "en": "Tengok perangai kau berdua, teringat Aki satu cerita.",
        "pa": "Looking at the both of you reminds me of a story.",
        "vi": "Nhìn hai cháu khiến ông nhớ đến một câu chuyện."
    },
    {
        "start": "00:02:27,800",
        "end": "00:02:29,080",
        "en": "Cerita?",
        "pa": "A story? Let's hear it!",
        "vi": "Một câu chuyện? Kể đi ông!"
    },
    {
        "start": "00:02:29,160",
        "end": "00:02:31,560",
        "en": "Nak dengar!",
        "pa": "",
        "vi": ""
    },
    {
        "start": "00:02:33,280",
        "end": "00:02:35,640",
        "en": "Cucu-cucu Aki inilah.",
        "pa": "The two of you…",
        "vi": "Hai cái đứa này…"
    },
    {
        "start": "00:02:37,240",
        "end": "00:02:40,000",
        "en": "Pada zaman dahulu…",
        "pa": "Once upon a time…",
        "vi": "Ngày xửa ngày xưa…"
    },
    {
        "start": "00:02:45,160",
        "end": "00:02:46,200",
        "en": "Sedapnya!",
        "pa": "It's delicious!",
        "vi": "Ngon quá!"
    },
    {
        "start": "00:02:56,360",
        "end": "00:02:57,720",
        "en": "- Kera! - Apa?",
        "pa": "Kera, come down here and eat with us.",
        "vi": "Kera, xuống đây và ăn với chúng tôi đi."
    },
    {
        "start": "00:02:58,320",
        "end": "00:03:00,360",
        "en": "Marilah turun makan bersama kami.",
        "pa": "",
        "vi": ""
    },
    {
        "start": "00:03:01,800",
        "end": "00:03:04,000",
        "en": "Boleh kita berbincang hal ehwal semasa.",
        "pa": "We can talk about current issues.",
        "vi": "Chúng ta có thể tán gẫu về những chuyện gần đây."
    },
    {
        "start": "00:03:05,920",
        "end": "00:03:07,080",
        "en": "Tak nak.",
        "pa": "No way…",
        "vi": "Không đời nào…"
    },
    {
        "start": "00:03:11,080",
        "end": "00:03:12,120",
        "en": "Apalah.",
        "pa": "It's just a waste of time.",
        "vi": "Chỉ tổ phí thời gian."
    },
    {
        "start": "00:03:13,720",
        "end": "00:03:15,440",
        "en": "Tak habis-habis kacau aku.",
        "pa": "Why do they keep inviting me?",
        "vi": "Sao họ cứ rủ rê mình vậy nhỉ?"
    },
    {
        "start": "00:03:16,440",
        "end": "00:03:19,960",
        "en": "Kera memang begitu, sombong! Susah nak ajak berbincang.",
        "pa": "Kera is arrogant always like that.",
        "vi": "Kera lúc nào cũng kiêu ngạo như thế."
    },
    {
        "start": "00:03:20,840",
        "end": "00:03:23,120",
        "en": "Nak tolong jauh sekali.",
        "pa": "It's so difficult to talk to him, let alone help.",
        "vi": "Nói chuyện với cậu ta còn khó, đừng nói chi đến việc giúp đỡ."
    },
    {
        "start": "00:03:25,760",
        "end": "00:03:30,200",
        "en": "Biarkanlah. Asalkan dia tak kacau kita.",
        "pa": "Let him be, as long as he doesn't bother any of us.",
        "vi": "Cứ kệ cậu ta, miễn là cậu ta không làm phiền chúng ta là được."
    },
    {
        "start": "00:03:30,280",
        "end": "00:03:31,560",
        "en": "Tak kacau?",
        "pa": "Doesn't bother?! Kera likes to steal our food.",
        "vi": "Không làm phiền? Kera thích trộm thức ăn của chúng ta."
    },
    {
        "start": "00:03:32,160",
        "end": "00:03:34,800",
        "en": "Kera suka mencuri makanan kami.",
        "pa": "",
        "vi": ""
    },
    {
        "start": "00:03:34,880",
        "end": "00:03:36,400",
        "en": "Nampakkah?",
        "pa": "Did you see it?",
        "vi": "Các cậu có nhìn thấy không?"
    },
    {
        "start": "00:03:36,480",
        "end": "00:03:38,440",
        "en": "Nampak!",
        "pa": "We did.",
        "vi": "Có chứ."
    },
    {
        "start": "00:03:41,240",
        "end": "00:03:42,880",
        "en": "Dahlah tak nak makan dengan kami.",
        "pa": "He doesn't want to eat with us.",
        "vi": "Cậu ta không muốn ăn với chúng ta."
    },
    {
        "start": "00:03:49,400",
        "end": "00:03:51,920",
        "en": "Hari ini juga aku kena jemput.",
        "pa": "I must invite them today.",
        "vi": "Mình phải mời họ vào hôm nay."
    },
    {
        "start": "00:04:28,040",
        "end": "00:04:30,080",
        "en": "Apa yang Tupai bawa?",
        "pa": "What is Tupai holding?",
        "vi": "Tupai đang cầm cái gì thế?"
    },
    {
        "start": "00:04:32,200",
        "end": "00:04:33,520",
        "en": "Ikutlah.",
        "pa": "I'll follow him.",
        "vi": "Mình sẽ đi theo lão."
    },
    {
        "start": "00:04:39,360",
        "end": "00:04:40,640",
        "en": "Sedapnya!",
        "pa": "Delicious!",
        "vi": "Ngon quá!"
    },
    {
        "start": "00:04:44,440",
        "end": "00:04:45,280",
        "en": "Sedap!",
        "pa": "Tasty!",
        "vi": "Ngon quá!"
    },
    {
        "start": "00:04:46,040",
        "end": "00:04:48,200",
        "en": "Manis!",
        "pa": "So sweet!",
        "vi": "Ngọt quá!"
    },
    {
        "start": "00:04:56,400",
        "end": "00:04:58,000",
        "en": "Tupai!",
        "pa": "Tupai.",
        "vi": "Tupai."
    },
    {
        "start": "00:04:58,080",
        "end": "00:04:59,000",
        "en": "Nak?",
        "pa": "Do you want some?",
        "vi": "Ông muốn ăn không?"
    },
    {
        "start": "00:05:01,320",
        "end": "00:05:05,400",
        "en": "Terima kasih. Lain kali sajalah. Aku nak cepat.",
        "pa": "Thank you. Maybe next time. I'm in a hurry.",
        "vi": "Cảm ơn. Có lẽ để lần sau. Ta đang vội."
    },
    {
        "start": "00:05:29,840",
        "end": "00:05:33,560",
        "en": "Majlis Hari Jadi? Mesti banyak makanan.",
        "pa": "BIRTHDAY PARTY\n A birthday celebration? There must be lots of food.",
        "vi": "TIỆC SINH NHẬT\n Một buổi tiệc sinh nhật? Chắc hẳn sẽ có rất nhiều thức ăn."
    },
    {
        "start": "00:05:34,640",
        "end": "00:05:36,240",
        "en": "Makanan?",
        "pa": "Food.",
        "vi": "Thức ăn."
    },
    {
        "start": "00:05:43,840",
        "end": "00:05:45,240",
        "en": "Tolong!",
        "pa": "Help!",
        "vi": "Cứu tôi với!"
    },
    {
        "start": "00:06:05,480",
        "end": "00:06:09,560",
        "en": "Apalah kau Gajah. Dengar saja makanan, terus kelam-kabut.",
        "pa": "You're so clumsy, Gajah.\n As soon as you hear food, you get so excited.",
        "vi": "Cậu thật vụng về, Gajah.\n Vừa nghe đến thức ăn là cậu phấn khích lên ngay."
    },
    {
        "start": "00:06:11,320",
        "end": "00:06:13,040",
        "en": "Gajah, makan saja tahu.",
        "pa": "Clumsy Gajah!",
        "vi": ""
    },
    {
        "start": "00:06:15,840",
        "end": "00:06:17,880",
        "en": "Datang, jangan tak datang.",
        "pa": "Do come!",
        "vi": "Nhớ đến nhé!"
    },
    {
        "start": "00:06:18,600",
        "end": "00:06:20,560",
        "en": "Kami mesti datang!",
        "pa": "We definitely will!",
        "vi": "Chắc chắn chúng tôi sẽ đến!"
    },
    {
        "start": "00:06:20,640",
        "end": "00:06:23,600",
        "en": "- Bagus! Aku nak pergi jemput Kera pula. - Jangan!",
        "pa": "Good! I'm going to invite Kera now.\n Don't!",
        "vi": "Tốt! Giờ ta đi mời Kera đây.\n Đừng!"
    },
    {
        "start": "00:06:26,840",
        "end": "00:06:28,160",
        "en": "Kenapa jangan?",
        "pa": "Why not?",
        "vi": "Sao vậy?"
    },
    {
        "start": "00:06:28,840",
        "end": "00:06:30,720",
        "en": "Kera mesti takkan datang.",
        "pa": "Kera won't come. He doesn't like to be with any of us!",
        "vi": "Kera sẽ không đến đâu. Cậu ta không thích ở cùng với bất cứ ai!"
    },
    {
        "start": "00:06:30,800",
        "end": "00:06:32,600",
        "en": "Dia tak suka bergaul dengan kita semua.",
        "pa": "",
        "vi": ""
    },
    {
        "start": "00:06:32,680",
        "end": "00:06:34,440",
        "en": "Ya! Macam \"Kera sumbang\".",
        "pa": "Yes! Just like the odd ape out.",
        "vi": "Phải! Giống như con vượn lập dị."
    },
    {
        "start": "00:06:36,640",
        "end": "00:06:38,920",
        "en": "Aku monyetlah! Bukan kera!",
        "pa": "I'm Monyet, not an ape.",
        "vi": "Tôi là Monyet, không phải vượn."
    },
    {
        "start": "00:06:40,320",
        "end": "00:06:42,960",
        "en": "Apa? Aku!",
        "pa": "What? I'm…",
        "vi": "Cái gì? Mình…"
    },
    {
        "start": "00:06:43,480",
        "end": "00:06:44,760",
        "en": "Kera sumbang!",
        "pa": "The odd man out?",
        "vi": "Là kẻ lập dị?"
    },
    {
        "start": "00:06:54,200",
        "end": "00:06:56,440",
        "en": "Lama lagi ke nak sampai?",
        "pa": "How much further?",
        "vi": "Còn bao lâu nữa?"
    },
    {
        "start": "00:06:56,520",
        "end": "00:06:58,160",
        "en": "Dua bulan.",
        "pa": "In two months, two months.",
        "vi": "Hai tháng."
    },
    {
        "start": "00:06:58,240",
        "end": "00:06:59,920",
        "en": "Kau tak habis-habis dua bulan.",
        "pa": "Stop it with the two months.",
        "vi": "Thôi cái trò hai tháng đó đi."
    },
    {
        "start": "00:07:00,000",
        "end": "00:07:01,480",
        "en": "Kau ada nampak Serama?",
        "pa": "-Have you seen Serama? -Let him be.",
        "vi": "Cậu có thấy Serama không?"
    },
    {
        "start": "00:07:01,560",
        "end": "00:07:04,120",
        "en": "Biarkanlah dia, aku dah ajak dah.",
        "pa": "",
        "vi": "Cứ kệ cậu ta đi."
    },
    {
        "start": "00:07:04,760",
        "end": "00:07:08,040",
        "en": "Pesta!",
        "pa": "Festival.",
        "vi": "Đi ăn tiệc là đi ăn tiệc."
    },
    {
        "start": "00:07:12,480",
        "end": "00:07:16,640",
        "en": "Semua dijemput, tapi aku dilupakan. Kenapa?",
        "pa": "Everyone is invited, except for me! Why is that?",
        "vi": "Mọi người đều được mời trừ mình ra! Tại sao lại như thế?"
    },
    {
        "start": "00:07:19,120",
        "end": "00:07:21,680",
        "en": "Datang, jangan tak datang.",
        "pa": "Come, don't forget it.",
        "vi": "Đến nhé, đừng có quên đấy."
    },
    {
        "start": "00:07:25,960",
        "end": "00:07:26,840",
        "en": "Baiklah.",
        "pa": "Very well.",
        "vi": "Dĩ nhiên rồi."
    },
    {
        "start": "00:07:30,600",
        "end": "00:07:34,960",
        "en": "Aku akan datang. Paling awal.",
        "pa": "I will come… as the first guest.",
        "vi": "Mình sẽ là… vị khách đến đầu tiên."
    },
    {
        "start": "00:07:41,080",
        "end": "00:07:42,240",
        "en": "Boleh aku makan banyak-banyak.",
        "pa": "I'm going to eat a lot!",
        "vi": "Tôi sẽ ăn thật là nhiều!"
    },
    {
        "start": "00:07:42,960",
        "end": "00:07:44,640",
        "en": "Kerbau kau nak bagi hadiah apa?",
        "pa": "What presents are you going to give him?",
        "vi": "Cậu sẽ tặng quà gì cho ông ấy?"
    },
    {
        "start": "00:07:45,920",
        "end": "00:07:48,040",
        "en": "Hadiah? Mana ada.",
        "pa": "Presents?\n I don't have a present.",
        "vi": "Quà à?\n Tôi không có quà."
    },
    {
        "start": "00:07:49,520",
        "end": "00:07:51,280",
        "en": "Tak tulis pun.",
        "pa": "It didn't say here.",
        "vi": "Trong này đâu có viết."
    },
    {
        "start": "00:07:52,800",
        "end": "00:07:55,480",
        "en": "Kalau begitu kita pergi makan sajalah.",
        "pa": "So then we'll just go there to eat.",
        "vi": "Vậy chúng ta cứ việc đến đó và ăn thôi."
    },
    {
        "start": "00:07:55,560",
        "end": "00:07:57,520",
        "en": "Makan apa?",
        "pa": "What are you talking about?",
        "vi": "Hai cậu đang nói gì thế?"
    },
    {
        "start": "00:07:57,600",
        "end": "00:07:59,560",
        "en": "- Kancil! - Hai!",
        "pa": "Kancil! Tupai is organizing a birthday celebration tomorrow.",
        "vi": "Kancil! Tupai đang chuẩn bị một bữa tiệc sinh nhật vào ngày mai."
    },
    {
        "start": "00:07:59,640",
        "end": "00:08:03,120",
        "en": "- Esok Tupai buat majlis hari jadi. - Betul!",
        "pa": "",
        "vi": ""
    },
    {
        "start": "00:08:03,200",
        "end": "00:08:06,760",
        "en": "Ada banyak makanan kegemaran kita.",
        "pa": "-Right! -There's going\n to be lots of our favorite foods.",
        "vi": "Sẽ có rất nhiều\n thức ăn mà chúng ta thích."
    },
    {
        "start": "00:08:06,840",
        "end": "00:08:09,520",
        "en": "Ya! Kau pergi tak?",
        "pa": "Are you going?",
        "vi": "Cậu có đi không?"
    },
    {
        "start": "00:08:10,960",
        "end": "00:08:12,320",
        "en": "Ya, aku pergi.",
        "pa": "Yes, I'm going.",
        "vi": "Có chứ."
    },
    {
        "start": "00:08:12,400",
        "end": "00:08:14,040",
        "en": "- Tak sabar aku nak… - Hore!",
        "pa": "I'm so excited to go!",
        "vi": "Tôi nôn nao đến dự tiệc quá!"
    },
    {
        "start": "00:08:42,720",
        "end": "00:08:46,960",
        "en": "Jangan cemarkan persekitaran. Nanti udara tak sihat.",
        "pa": "Don't pollute the environment. We'll get air pollution.",
        "vi": "Đừng gây ô nhiễm môi trường. Không khí sẽ bị ô nhiễm đấy."
    },
    {
        "start": "00:08:48,480",
        "end": "00:08:51,800",
        "en": "Hai, Kancil. Mana kau menghilang?",
        "pa": "Kancil, where did you go?",
        "vi": "Kancil, cậu đã đi đâu vậy?"
    },
    {
        "start": "00:08:52,760",
        "end": "00:08:56,480",
        "en": "Dah lama aku cari. Hari ini, hari jadi aku.",
        "pa": "I've been looking for you. Today is my birthday celebration.",
        "vi": "Ta tìm cậu nãy giờ. Ngày mai là tiệc sinh nhật của ta."
    },
    {
        "start": "00:08:57,240",
        "end": "00:09:01,920",
        "en": "Aku tahu. Sebab itu aku datang nak tolong kau buat persiapan.",
        "pa": "I know! That's why I came, to help with the preparation.",
        "vi": "Tôi biết! Thế nên tôi mới đến để giúp ông chuẩn bị đây."
    },
    {
        "start": "00:09:03,600",
        "end": "00:09:06,480",
        "en": "Terima kasih.",
        "pa": "Thank you.",
        "vi": "Cảm ơn nhé."
    },
    {
        "start": "00:09:07,160",
        "end": "00:09:08,720",
        "en": "Mari kita mulakan cepat.",
        "pa": "Where are…",
        "vi": "Ở đâu có…"
    },
    {
        "start": "00:10:04,800",
        "end": "00:10:08,960",
        "en": "",
        "pa": "BIRTHDAY PARTY",
        "vi": "TIỆC SINH NHẬT"
    },
    {
        "start": "00:10:16,480",
        "end": "00:10:18,920",
        "en": "Sekarang semuanya sudah bersih.",
        "pa": "Now everything is clean.",
        "vi": "Giờ mọi thứ đều sạch đẹp rồi."
    },
    {
        "start": "00:10:21,760",
        "end": "00:10:25,800",
        "en": "Aku akan menyiapkan hidangan untuk para tetamu pula.",
        "pa": "I'm going to…",
        "vi": "Ta sẽ…"
    },
    {
        "start": "00:10:26,920",
        "end": "00:10:29,120",
        "en": "Banyaknya makanan.",
        "pa": "There's so much food! It looks so good too. I can't wait!",
        "vi": "Nhiều thức ăn quá! Trông cũng ngon nữa. Mình không đợi nổi!"
    },
    {
        "start": "00:10:29,640",
        "end": "00:10:31,440",
        "en": "Sedap-sedap pula itu.",
        "pa": "",
        "vi": ""
    },
    {
        "start": "00:10:32,480",
        "end": "00:10:34,360",
        "en": "Tak sabarnya aku.",
        "pa": "",
        "vi": ""
    },
    {
        "start": "00:10:55,440",
        "end": "00:10:57,520",
        "en": "Tupai, ini hari jadi kau yang ke berapa?",
        "pa": "How old are you today?",
        "vi": "Hôm nay ông bao nhiêu tuổi vậy?"
    },
    {
        "start": "00:10:57,600",
        "end": "00:10:58,760",
        "en": "Rahsia.",
        "pa": "It's a secret.",
        "vi": "Đó là bí mật."
    },
    {
        "start": "00:10:59,280",
        "end": "00:11:00,120",
        "en": "Apa!",
        "pa": "",
        "vi": ""
    },
    {
        "start": "00:11:02,240",
        "end": "00:11:03,800",
        "en": "Kenapa Tupai?",
        "pa": "Why, Tupai?",
        "vi": "Sao thế Tupai?"
    },
    {
        "start": "00:11:04,760",
        "end": "00:11:06,360",
        "en": "Tengok hidangan kita.",
        "pa": "Look at our dishes. Looks like something's missing.",
        "vi": "Nhìn mấy cái đĩa của chúng ta đi. Hình như có cái gì đó bị mất."
    },
    {
        "start": "00:11:06,880",
        "end": "00:11:10,400",
        "en": "Macam ada kurang saja.",
        "pa": "",
        "vi": ""
    },
    {
        "start": "00:11:13,280",
        "end": "00:11:15,320",
        "en": "Tak apa, mari masuk dulu.",
        "pa": "Never mind, let's go back in first.",
        "vi": "Đừng bận tâm, cứ vào trong trước đã."
    },
    {
        "start": "00:11:18,800",
        "end": "00:11:20,680",
        "en": "Pisang!",
        "pa": "Banana!",
        "vi": "Chuối!"
    },
    {
        "start": "00:11:44,680",
        "end": "00:11:48,040",
        "en": "Si Kera yang mencuri makanan aku.",
        "pa": "Kera is the one who is stealing my food.",
        "vi": "Kera chính là kẻ trộm thức ăn của ta."
    },
    {
        "start": "00:11:48,120",
        "end": "00:11:51,240",
        "en": "Nanti tahulah aku nak ajar dia.",
        "pa": "I will teach him a lesson later.",
        "vi": "Ta sẽ dạy cho nó một bài học sau."
    },
    {
        "start": "00:11:51,320",
        "end": "00:11:53,680",
        "en": "Ya, kita mesti ajar.",
        "pa": "Yes, we must teach him.",
        "vi": "Phải, chúng ta phải làm thế."
    },
    {
        "start": "00:11:53,760",
        "end": "00:11:57,480",
        "en": "Sikapnya yang tidak suka bergaul dan suka mencuri",
        "pa": "His attitude of not mixing with others and stealing, it's too much.",
        "vi": "Cái tính không hòa đồng với người khác và tính trộm cắp của hắn thật là quá quắt."
    },
    {
        "start": "00:11:57,560",
        "end": "00:11:59,320",
        "en": "sudah melampau-lampau.",
        "pa": "",
        "vi": ""
    },
    {
        "start": "00:11:59,840",
        "end": "00:12:01,520",
        "en": "Tapi bagaimana?",
        "pa": "But what should we do?",
        "vi": "Nhưng ta phải làm gì mới được?"
    },
    {
        "start": "00:12:09,720",
        "end": "00:12:10,720",
        "en": "Hai!",
        "pa": "Hi!",
        "vi": "Xin chào!"
    },
    {
        "start": "00:12:21,840",
        "end": "00:12:23,600",
        "en": "Begitu!",
        "pa": "I get it!",
        "vi": "Mình biết rồi!"
    },
    {
        "start": "00:12:35,080",
        "end": "00:12:37,800",
        "en": "Apa agaknya yang di sembur oleh Tupai?",
        "pa": "What is Tupai spraying?",
        "vi": "Tupai đang phun gì thế nhỉ?"
    },
    {
        "start": "00:12:42,040",
        "end": "00:12:43,320",
        "en": "Ulat mati!",
        "pa": "Fruitworms!",
        "vi": "Sâu ăn quả!"
    },
    {
        "start": "00:12:43,920",
        "end": "00:12:46,320",
        "en": "Apa yang peliknya ulat mati dekat buah?",
        "pa": "What's so bad about a dead fruitworm in a fruit?",
        "vi": "Một con sâu đã ngỏm thì có gì ghê gớm chứ?"
    },
    {
        "start": "00:12:46,400",
        "end": "00:12:50,360",
        "en": "Yalah, Ara pun pernah jumpa ulat mati dalam buah.",
        "pa": "Even I found fruitworms in fruits.",
        "vi": "Cháu cũng từng thấy sâu trong trái cây rồi."
    },
    {
        "start": "00:12:51,200",
        "end": "00:12:55,720",
        "en": "Memang pun, tapi Kera tak suka bergaul.",
        "pa": "That is true, but Kera doesn't like to make friends,",
        "vi": "Đúng vậy, nhưng Kera không thích kết bạn,"
    },
    {
        "start": "00:12:55,800",
        "end": "00:12:58,040",
        "en": "Jadi dia ingat yang bukan-bukan.",
        "pa": "so he thought about something else.",
        "vi": "thế nên nó mới nghĩ đến thứ khác."
    },
    {
        "start": "00:12:58,120",
        "end": "00:12:59,920",
        "en": "Dia ingat apa?",
        "pa": "What was he thinking about?",
        "vi": "Nó nghĩ đến thứ gì vậy ông?"
    },
    {
        "start": "00:13:00,720",
        "end": "00:13:03,920",
        "en": "Dia ingat Tupai…",
        "pa": "He thought that Tupai…",
        "vi": "Nó nghĩ là Tupai…"
    },
    {
        "start": "00:13:09,440",
        "end": "00:13:11,600",
        "en": "Mesti dia menyembur racun.",
        "pa": "Of course he must have sprayed poison.",
        "vi": "Dĩ nhiên là lão phun thuốc độc rồi."
    },
    {
        "start": "00:13:12,640",
        "end": "00:13:15,400",
        "en": "Mesti makanan aku pun dia campurkan dengan racun.",
        "pa": "My food was definitely mixed with poison!",
        "vi": "Thức ăn của mình chắc chắn đã bị tẩm độc!"
    },
    {
        "start": "00:13:17,680",
        "end": "00:13:22,520",
        "en": "Aku tak bodoh. Aku tak nak mati kerana Si Tupai!",
        "pa": "I am not an idiot. I don't want to die because of Tupai!",
        "vi": "Mình đâu có ngốc. Mình không muốn chết vì lão Tupai!"
    },
    {
        "start": "00:13:24,840",
        "end": "00:13:26,640",
        "en": "Mujur aku tak makan lagi.",
        "pa": "Luckily I didn't eat it.",
        "vi": "May mà mình chưa ăn nó."
    },
    {
        "start": "00:13:39,440",
        "end": "00:13:42,520",
        "en": "Baguslah, sekarang Kera telah pergi.",
        "pa": "Very good, now Kera has left.",
        "vi": "Tốt lắm, giờ Kera đã đi rồi."
    },
    {
        "start": "00:13:43,040",
        "end": "00:13:47,640",
        "en": "Tentu dia marah kalau tahu yang aku hanya menyembur air biasa.",
        "pa": "He would be angry if he knew that I was just spraying water.",
        "vi": "Nếu biết ta chỉ phun nước, chắc nó sẽ tức giận lắm."
    },
    {
        "start": "00:13:53,880",
        "end": "00:13:57,200",
        "en": "Selamat hari jadi!",
        "pa": "Happy birthday to you Happy, happy, happy birthday to you",
        "vi": "Mừng sinh nhật đáng yêu Mừng sinh nhật dễ thương"
    },
    {
        "start": "00:13:57,280",
        "end": "00:14:00,560",
        "en": "Selamat hari jadi!",
        "pa": "",
        "vi": ""
    },
    {
        "start": "00:14:00,640",
        "end": "00:14:03,640",
        "en": "- Selamat harilah jadi… - Berhenti!",
        "pa": "Happy birthday to you…",
        "vi": "Mừng sinh nhật đáng yêu"
    },
    {
        "start": "00:14:04,600",
        "end": "00:14:06,760",
        "en": "Jangan pergi majlis Tupai!",
        "pa": "Stop! Don't go to Tupai's party!",
        "vi": "Dừng lại! Đừng đến dự sinh nhật của Tupai!"
    },
    {
        "start": "00:14:06,840",
        "end": "00:14:11,080",
        "en": "Aku nampak Tupai sembur racun pada semua makanan!",
        "pa": "I saw Tupai spraying poison on the food!",
        "vi": "Tôi đã thấy Tupai phun thuốc độc lên thức ăn đấy!"
    },
    {
        "start": "00:14:13,800",
        "end": "00:14:15,120",
        "en": "Kami tak percaya!",
        "pa": "We don't believe you!",
        "vi": "Chúng tôi không tin cậu!"
    },
    {
        "start": "00:14:15,200",
        "end": "00:14:18,200",
        "en": "Ya! Aku nampak sendiri.",
        "pa": "It's true! I saw it with my own eyes.",
        "vi": "Thật mà! Chính mắt tôi đã trông thấy."
    },
    {
        "start": "00:14:19,400",
        "end": "00:14:21,760",
        "en": "Tupai kawan kami! Kami mesti pergi.",
        "pa": "Tupai is our friend! We must go.",
        "vi": "Tupai là bạn của chúng tôi! Chúng tôi phải đến đó."
    },
    {
        "start": "00:14:22,640",
        "end": "00:14:24,440",
        "en": "Ya! Kau tak nak pergi, tak apa!",
        "pa": "Yes! If you don't want to, that's fine! You're not even our friend.",
        "vi": "Phải! Nếu cậu không muốn đi thì thôi! Cậu đâu phải bạn của chúng tôi."
    },
    {
        "start": "00:14:24,520",
        "end": "00:14:27,120",
        "en": "Kau bukan kawan kami pun.",
        "pa": "",
        "vi": ""
    },
    {
        "start": "00:14:27,200",
        "end": "00:14:29,840",
        "en": "Jangan layan Kera. Mari kita pergi cepat.",
        "pa": "Just ignore Kera, let's just go.",
        "vi": "Cứ mặc kệ Kera, mình đi thôi."
    },
    {
        "start": "00:14:30,880",
        "end": "00:14:35,600",
        "en": "Selamat hari jadi!",
        "pa": "Happy birthday to you",
        "vi": "Mừng sinh nhật đáng yêu"
    },
    {
        "start": "00:14:35,680",
        "end": "00:14:37,120",
        "en": "Kau ingat.",
        "pa": "You start first, okay?",
        "vi": "Cậu bắt đầu trước, được chứ?"
    },
    {
        "start": "00:15:04,760",
        "end": "00:15:06,200",
        "en": "Selamat datang!",
        "pa": "Welcome!",
        "vi": "Chào mừng!"
    },
    {
        "start": "00:15:06,840",
        "end": "00:15:08,880",
        "en": "Selamat hari jadi, Tupai!",
        "pa": "Happy birthday, Tupai!",
        "vi": "Chúc mừng sinh nhật Tupai!"
    },
    {
        "start": "00:15:10,360",
        "end": "00:15:13,120",
        "en": "Terima kasih. Mari masuk.",
        "pa": "-Thank you. Please come in. -You're welcome.",
        "vi": "- Cảm ơn. Mời vào trong. - Không có chi."
    },
    {
        "start": "00:15:17,200",
        "end": "00:15:19,960",
        "en": "Jemput makan. Habiskan.",
        "pa": "Go ahead and eat.",
        "vi": "Cứ tự nhiên ăn đi nào."
    },
    {
        "start": "00:15:20,920",
        "end": "00:15:22,960",
        "en": "Makanan!",
        "pa": "Food!",
        "vi": "Thức ăn!"
    },
    {
        "start": "00:15:24,760",
        "end": "00:15:25,960",
        "en": "Jangan…",
        "pa": "Don't!",
        "vi": "Đừng!"
    },
    {
        "start": "00:15:47,920",
        "end": "00:15:48,920",
        "en": "Kenapa tak makan?",
        "pa": "Why aren't you eating?",
        "vi": "Sao cả hai không ăn?"
    },
    {
        "start": "00:15:50,560",
        "end": "00:15:53,960",
        "en": "Mestilah takut! Kera kata, makanan beracun.",
        "pa": "We're scared! Kera said the food is poisoned!",
        "vi": "Chúng tôi sợ! Kera nói là đồ ăn đã bị tẩm độc!"
    },
    {
        "start": "00:15:57,200",
        "end": "00:15:59,080",
        "en": "Mereka dah terpedaya!",
        "pa": "They got tricked!",
        "vi": "Họ bị lừa rồi!"
    },
    {
        "start": "00:16:03,680",
        "end": "00:16:05,200",
        "en": "Percaya!",
        "pa": "",
        "vi": ""
    },
    {
        "start": "00:16:05,280",
        "end": "00:16:06,480",
        "en": "Sebenarnya…",
        "pa": "Actually…\n THIS IS WHAT REALLY HAPPENED",
        "vi": "Thật ra…\n SỰ THẬT LÀ THẾ NÀY"
    },
    {
        "start": "00:16:20,360",
        "end": "00:16:21,680",
        "en": "Kera tak patut mencuri!",
        "pa": "Kera shouldn't steal. He should have just come with us.",
        "vi": "Kera không nên ăn trộm. Lẽ ra cậu ta nên đi với chúng ta."
    },
    {
        "start": "00:16:21,760",
        "end": "00:16:23,720",
        "en": "Datanglah makan bersama-sama.",
        "pa": "",
        "vi": ""
    },
    {
        "start": "00:16:24,400",
        "end": "00:16:26,400",
        "en": "Rasakan! Kali ini,",
        "pa": "Take that! This time, he got tricked.",
        "vi": "Đáng đời! Lần này, cậu ta đã bị lừa."
    },
    {
        "start": "00:16:26,480",
        "end": "00:16:29,920",
        "en": "dia pula yang tertipu.",
        "pa": "",
        "vi": ""
    },
    {
        "start": "00:16:31,000",
        "end": "00:16:34,880",
        "en": "Kesian Kera. Dahlah tak ada kawan, kena tipu pula.",
        "pa": "Poor Kera. He has no friends, and now he got tricked.",
        "vi": "Kera đáng thương. Cậu ta không có bạn, và giờ lại bị lừa nữa."
    },
    {
        "start": "00:16:34,960",
        "end": "00:16:38,960",
        "en": "Biar dia tahu bagaimana seksanya hidup tanpa kawan-kawan",
        "pa": "Let him feel what it's like without friends and getting tricked like this.",
        "vi": "Cứ để cậu ta biết không có bạn và bị lừa là như thế nào."
    },
    {
        "start": "00:16:39,040",
        "end": "00:16:40,360",
        "en": "dan sering ditipu begini.",
        "pa": "",
        "vi": ""
    },
    {
        "start": "00:16:40,440",
        "end": "00:16:43,480",
        "en": "Apa? Aku ditipu!",
        "pa": "What? I got tricked!",
        "vi": "Gì cơ? Mình bị lừa!"
    },
    {
        "start": "00:16:44,800",
        "end": "00:16:46,040",
        "en": "Ini tidak adil!",
        "pa": "This is not fair!",
        "vi": "Thế này không công bằng!"
    },
    {
        "start": "00:16:46,120",
        "end": "00:16:48,920",
        "en": "Ya. Untuk memberi pengajaran.",
        "pa": "It is. It's to teach you a lesson.",
        "vi": "Có chứ. Cái đó là để dạy cho cậu một bài học."
    },
    {
        "start": "00:16:50,400",
        "end": "00:16:52,720",
        "en": "Cuba tengok binatang-binatang lain,",
        "pa": "Take a look at the other animals, living peacefully and helping each other.",
        "vi": "Hãy nhìn những con thú khác đi, họ sống hòa thuận và giúp đỡ lẫn nhau."
    },
    {
        "start": "00:16:52,800",
        "end": "00:16:56,720",
        "en": "hidup aman damai dan saling tolong menolong sesama sendiri.",
        "pa": "",
        "vi": ""
    },
    {
        "start": "00:16:58,160",
        "end": "00:17:01,960",
        "en": "Bukan macam kau. Hidup menyendiri dan suka mencuri.",
        "pa": "Unlike you, a loner who's always stealing.",
        "vi": "Không như cậu, một kẻ lạc loài lúc nào cũng trộm cắp."
    },
    {
        "start": "00:17:02,520",
        "end": "00:17:03,680",
        "en": "Yalah.",
        "pa": "That's true.",
        "vi": "Đúng vậy."
    },
    {
        "start": "00:17:04,319",
        "end": "00:17:06,000",
        "en": "Tak malu.",
        "pa": "Shameful.",
        "vi": "Thật xấu hổ."
    },
    {
        "start": "00:17:06,079",
        "end": "00:17:06,920",
        "en": "Kera sumbang.",
        "pa": "Odd man out!",
        "vi": "Đồ lập dị!"
    },
    {
        "start": "00:17:08,800",
        "end": "00:17:10,680",
        "en": "Pencuri!",
        "pa": "Thief!",
        "vi": "Kẻ trộm!"
    },
    {
        "start": "00:17:11,240",
        "end": "00:17:14,359",
        "en": "Kera sumbang!",
        "pa": "Shameful.",
        "vi": "Thật xấu hổ."
    },
    {
        "start": "00:17:14,440",
        "end": "00:17:17,200",
        "en": "Pencuri!",
        "pa": "Odd man out!",
        "vi": "Đồ lập dị!"
    },
    {
        "start": "00:17:20,599",
        "end": "00:17:24,560",
        "en": "Aku minta maaf kerana mencuri makanan tadi.",
        "pa": "I'm sorry I stole your food just now.",
        "vi": "Tôi xin lỗi vì lúc nãy đã trộm thức ăn của ông."
    },
    {
        "start": "00:17:24,640",
        "end": "00:17:27,800",
        "en": "Aku maafkan. Tapi janji,",
        "pa": "I forgive you.",
        "vi": "Ta tha lỗi cho cậu."
    },
    {
        "start": "00:17:27,880",
        "end": "00:17:30,000",
        "en": "jangan mencuri lagi",
        "pa": "But you must promise to stop stealing and try to make friends.",
        "vi": "Nhưng cậu phải hứa không trộm cắp nữa và cố gắng kết bạn đấy."
    },
    {
        "start": "00:17:30,080",
        "end": "00:17:33,560",
        "en": "dan jangan mengasingkan diri dari kami semua.",
        "pa": "",
        "vi": ""
    },
    {
        "start": "00:17:36,480",
        "end": "00:17:38,080",
        "en": "Aku janji! Lepas ini,",
        "pa": "I promise! After this I'll be a good friend!",
        "vi": "Tôi hứa! Sau việc này, tôi sẽ là một người bạn tốt!"
    },
    {
        "start": "00:17:38,160",
        "end": "00:17:41,440",
        "en": "aku akan jadi kawan yang paling baik.",
        "pa": "",
        "vi": ""
    },
    {
        "start": "00:17:47,360",
        "end": "00:17:50,120",
        "en": "Mari kita berhibur!",
        "pa": "Now, let's party!",
        "vi": "Giờ thì mở tiệc thôi!"
    },
    {
        "start": "00:18:26,200",
        "end": "00:18:28,920",
        "en": "Begitulah kisah \"Kera sumbang\".",
        "pa": "And that's the story of the odd man out, just like the two of you.",
        "vi": "Và đó là câu chuyện về kẻ lập dị, giống như hai cháu vậy."
    },
    {
        "start": "00:18:29,000",
        "end": "00:18:30,640",
        "en": "Sama macam kau berdua.",
        "pa": "",
        "vi": ""
    },
    {
        "start": "00:18:30,720",
        "end": "00:18:33,760",
        "en": "Asyik nak bersendiri saja. Tak nak berkawan.",
        "pa": "Always wanting to be by yourselves and not making friends.",
        "vi": "Lúc nào cũng muốn chơi một mình và không kết bạn với ai."
    },
    {
        "start": "00:18:34,680",
        "end": "00:18:37,360",
        "en": "Yalah, kita orang ikut Aki.",
        "pa": "Alright… we'll follow you.",
        "vi": "Được rồi… chúng cháu sẽ đi theo ông."
    },
    {
        "start": "00:18:39,400",
        "end": "00:18:43,440",
        "en": "Papa Mama dah sampai. Tak payah pergi.",
        "pa": "Dad and mom are here. We don't need to go.",
        "vi": "Bố mẹ đến rồi. Chúng cháu không cần phải đi nữa."
    },
    {
        "start": "00:18:47,920",
        "end": "00:18:49,000",
        "en": "Mama!",
        "pa": "Mom!",
        "vi": "Mẹ!"
    },
    {
        "start": "00:18:52,400",
        "end": "00:18:54,080",
        "en": "Kenapa sampai awal sangat?",
        "pa": "Why are you here so early?",
        "vi": "Sao các con đến sớm thế?"
    },
    {
        "start": "00:18:57,120",
        "end": "00:18:59,920",
        "en": "Dah! Mari kita semua pergi kenduri.",
        "pa": "Alright! Let's all go to the ceremony.",
        "vi": "Được rồi! Tất cả cùng nhau đến dự lễ đi."
    },
    {
        "start": "00:19:00,000",
        "end": "00:19:02,920",
        "en": "Apa!",
        "pa": "No.",
        "vi": "Ôi không."
    },
    {
        "start": "00:19:06,120",
        "end": "00:19:08,440",
        "en": "Papa nak tengok gambar tadi.",
        "pa": "Papa, I want to see the pictures.",
        "vi": "Bố, con muốn xem ảnh."
    },
    {
        "start": "00:19:08,960",
        "end": "00:19:10,640",
        "en": "Ara nak tengok juga!",
        "pa": "I want to look at the pictures too!",
        "vi": "Con cũng muốn xem!"
    },
    {
        "start": "00:19:30,000",
        "end": "00:19:32,360",
        "en": "",
        "pa": "",
        "vi": "Biên dịch: Hoàng Nguyên"
    }
]